hadrodb/__init__.py
hadrodb/config.py
hadrodb/engine.py
hadrodb/record.py
hadrodb/version.py
hadrodb-0.0.3.dist-info/LICENSE
hadrodb-0.0.3.dist-info/METADATA
hadrodb-0.0.3.dist-info/NOTICES
hadrodb-0.0.3.dist-info/WHEEL
hadrodb-0.0.3.dist-info/top_level.txt
hadrodb-0.0.3.dist-info/RECORD
