Metadata-Version: 2.1
Name: hadrodb
Version: 0.0.3
Summary: KV Store
Home-page: https://github.com/mabel-dev/hadrodb/
Author: @joocer
Author-email: justin.joyce@joocer.com
Maintainer: @joocer
License-File: LICENSE
License-File: NOTICES
Requires-Dist: cityhash
Requires-Dist: ormsgpack
